doc2data/__init__.py
doc2data/pdf.py
doc2data/utils.py
doc2data/experimental/base_processors.py
doc2data/experimental/ocr.py
doc2data/experimental/preprocessing.py
doc2data/experimental/task_processors.py
doc2data/experimental/trainers.py
doc2data/experimental/utils.py
doc2data-0.2.0.dist-info/METADATA
doc2data-0.2.0.dist-info/WHEEL
doc2data-0.2.0.dist-info/licenses/LICENSE.txt
doc2data-0.2.0.dist-info/RECORD
