Metadata-Version: 2.1
Name: doc2data
Version: 0.2.0
Summary: Integrated document processing with machine learning.
Project-URL: Documentation, http://doc2data.readthedocs.io/
Project-URL: Issues, https://github.com/serge724/doc2data/issues
Project-URL: Source, https://github.com/serge724/doc2data
Author-email: Sergej Levich <sergej.levich@gmail.com>
License-File: LICENSE.txt
Keywords: deep learning,document processing,machine learning,pdf parsing
Classifier: Development Status :: 4 - Beta
Classifier: Programming Language :: Python
Classifier: Programming Language :: Python :: 3.7
Classifier: Programming Language :: Python :: 3.8
Classifier: Programming Language :: Python :: 3.9
Classifier: Programming Language :: Python :: 3.10
Classifier: Programming Language :: Python :: Implementation :: CPython
Classifier: Programming Language :: Python :: Implementation :: PyPy
Requires-Python: >=3.7
Requires-Dist: numpy>=1.21.6
Requires-Dist: pandas>=1.3.5
Requires-Dist: pillow>=9.0.0
Requires-Dist: pymupdf>=1.19.6
Requires-Dist: tqdm>=4.64.0
